gimme/__init__.py
gimme/attribute.py
gimme/exceptions.py
gimme/helpers.py
gimme/main.py
gimme/repository.py
gimme/resolvers.py
gimme/types.py
gimme_that-0.3.1.dist-info/LICENSE
gimme_that-0.3.1.dist-info/METADATA
gimme_that-0.3.1.dist-info/WHEEL
gimme_that-0.3.1.dist-info/top_level.txt
gimme_that-0.3.1.dist-info/RECORD
