Metadata-Version: 2.1
Name: gimme-that
Version: 0.3.1
Summary: Simple and flexible dependency injection framework.
Home-page: https://github.com/elfjes/gimme-that
Author: Pelle Koster
License: MIT
Project-URL: Documentation, https://gimme-that.readthedocs.io/
Keywords: inversion-of-control IoC DI dependency-injection
Classifier: Development Status :: 3 - Alpha
Classifier: Intended Audience :: Developers
Classifier: License :: OSI Approved :: MIT License
Classifier: Operating System :: OS Independent
Classifier: Programming Language :: Python
Classifier: Programming Language :: Python :: 3.7
Classifier: Programming Language :: Python :: 3.8
Classifier: Programming Language :: Python :: 3.9
Classifier: Programming Language :: Python :: 3.10
Classifier: Programming Language :: Python :: 3 :: Only
Classifier: Topic :: Software Development :: Libraries
Requires-Python: >=3.6
License-File: LICENSE
Provides-Extra: dev
Requires-Dist: pytest (==6.2.5) ; extra == 'dev'
Requires-Dist: pytest-cov (==3.0.0) ; extra == 'dev'
Requires-Dist: sphinx (==4.3.2) ; extra == 'dev'
Requires-Dist: sphinx-autodoc-typehints (==1.15.2) ; extra == 'dev'
Requires-Dist: pre-commit (==2.16.0) ; extra == 'dev'
Requires-Dist: flake8 (==4.0.1) ; extra == 'dev'
Requires-Dist: tox (==3.24.5) ; extra == 'dev'
Provides-Extra: docs
Requires-Dist: sphinx (==4.3.2) ; extra == 'docs'
Requires-Dist: sphinx-autodoc-typehints (==1.15.2) ; extra == 'docs'
Provides-Extra: test
Requires-Dist: pytest (==6.2.5) ; extra == 'test'
Requires-Dist: pytest-cov (==3.0.0) ; extra == 'test'
